{
  "type": "minecraft:crafting_shaped",
  "category": "equipment",
  "key": {
    "#": "minecraft:stick",
    "X": "#minecraft:gold_tool_materials"
  },
  "pattern": [
    "  X",
    " X ",
    "#  "
  ],
  "result": {
    "components": {
      "minecraft:item_name": {
        "translate": "item.fabled_roots.golden_rapier"
      },
      "minecraft:item_model": "fabled_roots:golden_rapier",
      "minecraft:rarity": "common",
      "minecraft:custom_data": {
        "fabled_roots": {
          "item": "golden_rapier",
          "type": "rapier"
        }
      },
      "minecraft:attribute_modifiers": [
        {
          "type": "minecraft:entity_interaction_range",
          "id": "fabled_roots:rapier_range",
          "amount": 1,
          "operation": "add_value",
          "slot": "mainhand",
          "display": {
            "type": "default"
          }
        },
        {
          "type": "minecraft:attack_damage",
          "id": "fabled_roots:rapier_attack",
          "amount": 2,
          "operation": "add_value",
          "slot": "mainhand"
        },
        {
          "type": "minecraft:attack_speed",
          "id": "fabled_roots:rapier_speed",
          "amount": -2,
          "operation": "add_value",
          "slot": "mainhand"
        }
      ],
      "minecraft:tooltip_style": "fabled_roots:palehearted",
                "swing_animation": {
                  "type": "stab",
                  "duration": 20
                }
    },
    "count": 1,
    "id": "minecraft:golden_sword"
  }
}